{
  "project_info": {
    "project_number": "741634543610",
    "firebase_url": "https://spaceshooterultimate-d958c-default-rtdb.firebaseio.com",
    "project_id": "spaceshooterultimate-d958c",
    "storage_bucket": "spaceshooterultimate-d958c.appspot.com"
  },
  "client": [
    {
      "client_info": {
        "mobilesdk_app_id": "1:741634543610:android:b1d1352c385c4ae3b81e43",
        "android_client_info": {
          "package_name": "com.juanpa.spaceshooterultimate"
        }
      },
      "oauth_client": [],
      "api_key": [
        {
          "current_key": "AIzaSyByhfabHaluUnEqZCR-C4l9Mc2Tg460A_c"
        }
      ],
      "services": {
        "appinvite_service": {
          "other_platform_oauth_client": []
        }
      }
    }
  ],
  "configuration_version": "1"
}